biothings_client/__init__.py
biothings_client/__version__.py
biothings_client/_dependencies.py
biothings_client/cache/__init__.py
biothings_client/cache/storage.py
biothings_client/client/__init__.py
biothings_client/client/asynchronous.py
biothings_client/client/base.py
biothings_client/client/definitions.py
biothings_client/client/exceptions.py
biothings_client/client/settings.py
biothings_client/docstring/__init__.py
biothings_client/docstring/chem.py
biothings_client/docstring/gene.py
biothings_client/docstring/variant.py
biothings_client/mixins/__init__.py
biothings_client/mixins/gene.py
biothings_client/mixins/variant.py
biothings_client/utils/__init__.py
biothings_client/utils/cache.py
biothings_client/utils/copy.py
biothings_client/utils/gene.py
biothings_client/utils/iteration.py
biothings_client/utils/join.py
biothings_client/utils/jsonld_utils.py
biothings_client/utils/score.py
biothings_client/utils/variant.py
biothings_client-0.4.0.dist-info/LICENSE.txt
biothings_client-0.4.0.dist-info/METADATA
biothings_client-0.4.0.dist-info/WHEEL
biothings_client-0.4.0.dist-info/top_level.txt
biothings_client-0.4.0.dist-info/zip-safe
biothings_client-0.4.0.dist-info/RECORD
