Metadata-Version: 2.2
Name: biothings_client
Version: 0.4.0
Summary: Python Client for BioThings API services.
Author: Cyrus Afrasiabi, Xinghua Zhou
Author-email: Everaldo Rodolpho <erodolpho@scripps.edu>, Johnathan Schaff <jschaff@scripps.edu>, Chunlei Wu <cwu@scripps.edu>
License: BSD-3-Clause
Project-URL: homepage, https://github.com/biothings/biothings_client.py
Project-URL: repository, https://github.com/biothings/biothings_client.py
Project-URL: documentation, https://biothings-clientpy.readthedocs.io
Keywords: biology,variant,gene,taxon,taxonomy,species,drug,chemical,disease,phenotype,geneset,annotation,web,service,client,api,mygene.info,myvariant.info,mychem.info,mydisease.info,mygeneset.info
Classifier: Programming Language :: Python :: 3
Classifier: Programming Language :: Python :: 3 :: Only
Classifier: Programming Language :: Python :: 3.6
Classifier: Programming Language :: Python :: 3.7
Classifier: Programming Language :: Python :: 3.8
Classifier: Programming Language :: Python :: 3.9
Classifier: Programming Language :: Python :: 3.10
Classifier: Programming Language :: Python :: 3.11
Classifier: Programming Language :: Python :: 3.12
Classifier: Programming Language :: Python :: 3.13
Classifier: Development Status :: 4 - Beta
Classifier: License :: OSI Approved :: BSD License
Classifier: Operating System :: POSIX
Classifier: Operating System :: MacOS :: MacOS X
Classifier: Operating System :: Microsoft :: Windows
Classifier: Operating System :: OS Independent
Classifier: Intended Audience :: Science/Research
Classifier: Intended Audience :: Developers
Classifier: Topic :: Utilities
Classifier: Topic :: Scientific/Engineering :: Bio-Informatics
Requires-Python: >=3.6
License-File: LICENSE.txt
Requires-Dist: httpx>=0.22.0
Requires-Dist: importlib-metadata; python_version < "3.8"
Provides-Extra: caching
Requires-Dist: anysqlite; python_version >= "3.8" and extra == "caching"
Requires-Dist: hishel[sqlite]; python_version >= "3.8" and extra == "caching"
Provides-Extra: dataframe
Requires-Dist: pandas>=1.1.5; extra == "dataframe"
Provides-Extra: jsonld
Requires-Dist: PyLD>=0.7.2; extra == "jsonld"
Provides-Extra: tests
Requires-Dist: pytest>=7.0.1; extra == "tests"
Requires-Dist: pytest-asyncio>=0.16.0; extra == "tests"
